exampleplayer/__init__.py
exampleplayer/player.py
exampleplayer_miloter-0.0.1.dist-info/LICENSE
exampleplayer_miloter-0.0.1.dist-info/METADATA
exampleplayer_miloter-0.0.1.dist-info/WHEEL
exampleplayer_miloter-0.0.1.dist-info/top_level.txt
exampleplayer_miloter-0.0.1.dist-info/RECORD
