Metadata-Version: 2.1
Name: exampleplayer_miloter
Version: 0.0.1
Summary: This is a reproductor of test
Author: miloter
License: MIT License
Project-URL: Homepage, https://facite.es
Project-URL: Issues, https://facite.es
Classifier: Programming Language :: Python :: 3
Classifier: License :: OSI Approved :: MIT License
Classifier: Operating System :: OS Independent
Requires-Python: >=3.8
License-File: LICENSE
